itkpocus/__init__.py
itkpocus/butterfly.py
itkpocus/clarius.py
itkpocus/interson.py
itkpocus/openigtlink.py
itkpocus/sonivate.py
itkpocus/sonoque.py
itkpocus/sonosite.py
itkpocus/util.py
itk_pocus-0.3.2.dist-info/LICENSE
itk_pocus-0.3.2.dist-info/WHEEL
itk_pocus-0.3.2.dist-info/METADATA
itk_pocus-0.3.2.dist-info/RECORD
