Metadata-Version: 2.1
Name: itk-pocus
Version: 0.3.2
Summary: ITKPOCUS - an open source library for image processing and AI of point-of-care ultrasound, based on ITK (https://pypi.org/project/itk/)
Home-page: https://github.com/KitwareMedical/ITKPOCUS
Author: Brad T. Moore
Author-email: brad.moore@kitware.com
Requires-Python: >=3.7
Classifier: License :: OSI Approved :: Apache Software License
Classifier: Topic :: Scientific/Engineering :: Image Processing
Classifier: Topic :: Scientific/Engineering :: Medical Science Apps.
Classifier: Programming Language :: Python :: 3
Classifier: Intended Audience :: Healthcare Industry
Classifier: Intended Audience :: Science/Research
Requires-Dist: itk>=5.2.0.post2
Requires-Dist: scikit-image
Requires-Dist: scipy
Requires-Dist: sk-video
Requires-Dist: numpy
